[{"country": "\u0412\u0435\u0441\u044c \u043c\u0438\u0440", "info": {"all_sick": "459 802 558", "sick_per_day": "1 723 383", "all_deaths": "6 045 865"}}, {"country": "\u0421\u043e\u0435\u0434\u0438\u043d\u0435\u043d\u043d\u044b\u0435 \u0428\u0442\u0430\u0442\u044b \u0410\u043c\u0435\u0440\u0438\u043a\u0438", "info": {"all_sick": "79 473 611", "sick_per_day": "55 480", "all_deaths": "963 926"}}, {"country": "\u0418\u043d\u0434\u0438\u044f", "info": {"all_sick": "42 996 062", "sick_per_day": "2 568", "all_deaths": "515 974"}}, {"country": "\u0411\u0440\u0430\u0437\u0438\u043b\u0438\u044f", "info": {"all_sick": "29 391 345", "sick_per_day": "16 512", "all_deaths": "655 557"}}, {"country": "\u0424\u0440\u0430\u043d\u0446\u0438\u044f", "info": {"all_sick": "22 889 446", "sick_per_day": "18 853", "all_deaths": "137 210"}}, {"country": "\u0412\u0435\u043b\u0438\u043a\u043e\u0431\u0440\u0438\u0442\u0430\u043d\u0438\u044f", "info": {"all_sick": "19 700 952", "sick_per_day": "170 467", "all_deaths": "162 873"}}, {"country": "\u0413\u0435\u0440\u043c\u0430\u043d\u0438\u044f", "info": {"all_sick": "17 470 663", "sick_per_day": "198 955", "all_deaths": "125 878"}}, {"country": "\u0420\u043e\u0441\u0441\u0438\u044f", "info": {"all_sick": "17 124 792", "sick_per_day": "40 120", "all_deaths": "354 157"}}, {"country": "\u0422\u0443\u0440\u0446\u0438\u044f", "info": {"all_sick": "14 576 069", "sick_per_day": "24 404", "all_deaths": "96 620"}}, {"country": "\u0418\u0442\u0430\u043b\u0438\u044f", "info": {"all_sick": "13 402 905", "sick_per_day": "29 698", "all_deaths": "156 997"}}, {"country": "\u0418\u0441\u043f\u0430\u043d\u0438\u044f", "info": {"all_sick": "11 223 974", "sick_per_day": "0", "all_deaths": "101 135"}}, {"country": "\u0410\u0440\u0433\u0435\u043d\u0442\u0438\u043d\u0430", "info": {"all_sick": "8 976 079", "sick_per_day": "4 647", "all_deaths": "127 257"}}, {"country": "\u041d\u0438\u0434\u0435\u0440\u043b\u0430\u043d\u0434\u044b", "info": {"all_sick": "7 298 195", "sick_per_day": "45 892", "all_deaths": "21 734"}}, {"country": "\u042e\u0436\u043d\u0430\u044f \u041a\u043e\u0440\u0435\u044f", "info": {"all_sick": "7 228 550", "sick_per_day": "362 328", "all_deaths": "10 888"}}, {"country": "\u0418\u0440\u0430\u043d", "info": {"all_sick": "7 126 906", "sick_per_day": "3 813", "all_deaths": "139 063"}}, {"country": "\u0412\u044c\u0435\u0442\u043d\u0430\u043c", "info": {"all_sick": "6 377 438", "sick_per_day": "264 790", "all_deaths": "41 477"}}, {"country": "\u041a\u043e\u043b\u0443\u043c\u0431\u0438\u044f", "info": {"all_sick": "6 077 288", "sick_per_day": "469", "all_deaths": "139 315"}}, {"country": "\u0418\u043d\u0434\u043e\u043d\u0435\u0437\u0438\u044f", "info": {"all_sick": "5 900 124", "sick_per_day": "9 629", "all_deaths": "152 437"}}, {"country": "\u041f\u043e\u043b\u044c\u0448\u0430", "info": {"all_sick": "5 823 982", "sick_per_day": "5 295", "all_deaths": "113 444"}}, {"country": "\u042f\u043f\u043e\u043d\u0438\u044f", "info": {"all_sick": "5 805 074", "sick_per_day": "32 359", "all_deaths": "26 274"}}, {"country": "\u041c\u0435\u043a\u0441\u0438\u043a\u0430", "info": {"all_sick": "5 607 845", "sick_per_day": "1 018", "all_deaths": "321 115"}}, {"country": "\u0423\u043a\u0440\u0430\u0438\u043d\u0430", "info": {"all_sick": "5 040 518", "sick_per_day": "0", "all_deaths": "112 459"}}, {"country": "\u041c\u0430\u043b\u0430\u0439\u0437\u0438\u044f", "info": {"all_sick": "3 845 601", "sick_per_day": "22 030", "all_deaths": "33 899"}}, {"country": "\u0418\u0437\u0440\u0430\u0438\u043b\u044c", "info": {"all_sick": "3 725 407", "sick_per_day": "5 970", "all_deaths": "10 392"}}, {"country": "\u042e\u0436\u043d\u0430\u044f \u0410\u0444\u0440\u0438\u043a\u0430", "info": {"all_sick": "3 695 175", "sick_per_day": "671", "all_deaths": "99 725"}}, {"country": "\u0427\u0435\u0445\u0438\u044f", "info": {"all_sick": "3 685 973", "sick_per_day": "0", "all_deaths": "39 155"}}, {"country": "\u0424\u0438\u043b\u0438\u043f\u043f\u0438\u043d\u044b", "info": {"all_sick": "3 671 293", "sick_per_day": "554", "all_deaths": "57 625"}}, {"country": "\u0411\u0435\u043b\u044c\u0433\u0438\u044f", "info": {"all_sick": "3 658 084", "sick_per_day": "18 032", "all_deaths": "30 445"}}, {"country": "\u0410\u0432\u0441\u0442\u0440\u0430\u043b\u0438\u044f", "info": {"all_sick": "3 651 709", "sick_per_day": "28 803", "all_deaths": "5 615"}}, {"country": "\u041f\u0435\u0440\u0443", "info": {"all_sick": "3 536 842", "sick_per_day": "346", "all_deaths": "211 579"}}, {"country": "\u041f\u043e\u0440\u0442\u0443\u0433\u0430\u043b\u0438\u044f", "info": {"all_sick": "3 413 013", "sick_per_day": "32 750", "all_deaths": "21 342"}}, {"country": "\u041a\u0430\u043d\u0430\u0434\u0430", "info": {"all_sick": "3 376 139", "sick_per_day": "4 079", "all_deaths": "37 327"}}, {"country": "\u0427\u0438\u043b\u0438", "info": {"all_sick": "3 313 242", "sick_per_day": "11 495", "all_deaths": "44 005"}}, {"country": "\u0422\u0430\u0438\u043b\u0430\u043d\u0434", "info": {"all_sick": "3 226 697", "sick_per_day": "19 742", "all_deaths": "23 848"}}, {"country": "\u0410\u0432\u0441\u0442\u0440\u0438\u044f", "info": {"all_sick": "3 188 147", "sick_per_day": "34 220", "all_deaths": "15 221"}}, {"country": "\u0428\u0432\u0435\u0439\u0446\u0430\u0440\u0438\u044f", "info": {"all_sick": "3 141 904", "sick_per_day": "69 146", "all_deaths": "13 286"}}, {"country": "\u0414\u0430\u043d\u0438\u044f", "info": {"all_sick": "2 958 497", "sick_per_day": "7 892", "all_deaths": "5 196"}}, {"country": "\u0420\u0443\u043c\u044b\u043d\u0438\u044f", "info": {"all_sick": "2 794 081", "sick_per_day": "2 087", "all_deaths": "64 381"}}, {"country": "\u0413\u0440\u0435\u0446\u0438\u044f", "info": {"all_sick": "2 658 296", "sick_per_day": "22 682", "all_deaths": "26 635"}}, {"country": "\u0428\u0432\u0435\u0446\u0438\u044f", "info": {"all_sick": "2 466 577", "sick_per_day": "0", "all_deaths": "17 798"}}, {"country": "\u0418\u0440\u0430\u043a", "info": {"all_sick": "2 313 370", "sick_per_day": "657", "all_deaths": "25 105"}}]